AUTHORS
ChangeLog
README
setup.cfg
setup.py
django_generate_fixtures/__init__.py
django_generate_fixtures.egg-info/PKG-INFO
django_generate_fixtures.egg-info/SOURCES.txt
django_generate_fixtures.egg-info/dependency_links.txt
django_generate_fixtures.egg-info/not-zip-safe
django_generate_fixtures.egg-info/pbr.json
django_generate_fixtures.egg-info/top_level.txt
django_generate_fixtures/management/__init__.py
django_generate_fixtures/management/commands/__init__.py
django_generate_fixtures/management/commands/generate_fixtures.py